{
  "1686300876867": {
    "id": "1686300876867",
    "title": "dev3",
    "description": "dev3",
    "tags": [
      "pick",
      "dick"
    ]
  },
  "1686313663619": {
    "id": "1686313663619",
    "title": "pickle",
    "description": "pickle",
    "tags": [
      "pickle"
    ]
  },
  "1686289978414": {
    "id": "1686289978414",
    "title": "dev2",
    "description": "dev2",
    "tags": [
      "pickle"
    ]
  },
  "1686289971411": {
    "id": "1686289971411",
    "title": "dev",
    "description": "dev",
    "tags": [
      "dick",
      "rick"
    ]
  },
  "1686313666998": {
    "id": "1686313666998",
    "title": "pickle",
    "description": "pickle",
    "tags": [
      "pickle"
    ]
  }
}